{
    "group0": {
        "dependency": {
            "dockerfile": null,
            "requirements_file": "requirements_0.txt"
        },
        "pieces": [
            "LoremIpsumGeneratorPiece",
            "DataConversionPiece",
            "GetItemFromArrayPiece",
            "HttpRequestPiece",
            "ImageFilterPiece",
            "StringConditionChecksPiece",
            "SaveImagePiece",
            "ToyDatasetsPiece",
            "SleepPiece",
            "YDataProfilingPiece",
            "GetDateTimePiece",
            "LogPiece",
            "PageScrapperPiece",
            "CustomPythonPiece",
            "StringOperationsPiece",
            "ToStringPiece"
        ],
        "secrets": [
            "TEST_SECRET"
        ],
        "source_image": "ghcr.io/iisas/default_domino_pieces:0.9.0-group0"
    }
}